{
    "key": "taxonomy_66f6fde24e40f",
    "title": "Client Types",
    "menu_order": 0,
    "active": true,
    "taxonomy": "client-type",
    "object_type": [
        "work"
    ],
    "advanced_configuration": 1,
    "import_source": "",
    "import_date": "",
    "labels": {
        "name": "Client Types",
        "singular_name": "Client Type",
        "menu_name": "Client Types",
        "all_items": "All Client Types",
        "edit_item": "Edit Client Type",
        "view_item": "View Client Type",
        "update_item": "Update Client Type",
        "add_new_item": "Add New Client Type",
        "new_item_name": "New Client Type Name",
        "parent_item": "Parent Client Type",
        "parent_item_colon": "Parent Client Type:",
        "search_items": "Search Client Types",
        "most_used": "",
        "not_found": "No client types found",
        "no_terms": "No client types",
        "name_field_description": "",
        "slug_field_description": "",
        "parent_field_description": "",
        "desc_field_description": "",
        "filter_by_item": "Filter by client type",
        "items_list_navigation": "Client Types list navigation",
        "items_list": "Client Types list",
        "back_to_items": "← Go to client types",
        "item_link": "Client Type Link",
        "item_link_description": "A link to a client type"
    },
    "description": "",
    "capabilities": {
        "manage_terms": "manage_categories",
        "edit_terms": "manage_categories",
        "delete_terms": "manage_categories",
        "assign_terms": "edit_posts"
    },
    "public": 1,
    "publicly_queryable": 0,
    "hierarchical": 1,
    "show_ui": 1,
    "show_in_menu": 1,
    "show_in_nav_menus": 1,
    "show_in_rest": 1,
    "rest_base": "",
    "rest_namespace": "wp\/v2",
    "rest_controller_class": "WP_REST_Terms_Controller",
    "show_tagcloud": 1,
    "show_in_quick_edit": 1,
    "show_admin_column": 1,
    "rewrite": {
        "permalink_rewrite": "taxonomy_key",
        "with_front": "0",
        "rewrite_hierarchical": "1"
    },
    "query_var": "taxonomy_key",
    "query_var_name": "",
    "default_term": {
        "default_term_enabled": "0"
    },
    "sort": 0,
    "meta_box": "default",
    "meta_box_cb": "",
    "meta_box_sanitize_cb": "",
    "modified": 1727462972
}
